Metadata-Version: 1.0
Name: collective.portlet.pythonscript
Version: 1.2
Summary: Portlet rendering collection of items returned by customizable Python scripts
Home-page: https://github.com/collective/collective.portlet.pythonscript
Author: Tomasz Mackowiak
Author-email: tomasz.mackowiak@stxnext.pl
License: GPLv2
Platform: UNKNOWN
Classifier: Environment :: Web Environment
Classifier: Framework :: Plone
Classifier: Framework :: Plone :: 4.1
Classifier: Framework :: Plone :: 4.2
Classifier: Framework :: Plone :: 4.3
Classifier: License :: OSI Approved :: GNU General Public License v2 (GPLv2)
Classifier: Operating System :: OS Independent
Classifier: Programming Language :: Python
Classifier: Programming Language :: Python :: 2.6
Classifier: Programming Language :: Python :: 2.7
Classifier: Topic :: Internet :: WWW/HTTP
Classifier: Topic :: Internet :: WWW/HTTP :: Dynamic Content
Classifier: Topic :: Software Development :: Libraries :: Python Modules
